usbserial4a/__init__.py
usbserial4a/cdcacmserial4a.py
usbserial4a/ch34xserial4a.py
usbserial4a/cp210xserial4a.py
usbserial4a/ftdiserial4a.py
usbserial4a/pl2303serial4a.py
usbserial4a/serial4a.py
usbserial4a/vidpid4a.py
usbserial4a-0.2.0.dist-info/METADATA
usbserial4a-0.2.0.dist-info/RECORD
usbserial4a-0.2.0.dist-info/WHEEL
usbserial4a-0.2.0.dist-info/top_level.txt
