Metadata-Version: 2.1
Name: usbserial4a
Version: 0.2.0
Summary: Python package for Kivy Android USB serial port.
Home-page: https://github.com/jacklinquan/usbserial4a
Author: Quan Lin
Author-email: jacklinquan@gmail.com
License: MIT
Platform: UNKNOWN
Classifier: Development Status :: 3 - Alpha
Classifier: License :: OSI Approved :: MIT License
Classifier: Operating System :: Android
Classifier: Programming Language :: Python :: 2
Classifier: Programming Language :: Python :: 2.7
Classifier: Programming Language :: Python :: 3
Requires-Dist: pyserial
Requires-Dist: usb4a
